Workbook

Sheet Inputs
B2: Investment Scenario Playground
B3: Edit the yellow cells below. Everything else recalculates automatically.
B5: Starting Balance ($) | C5: 0
B6: Monthly Contribution ($) | C6: 1000
B7: Monthly Price Growth (%) | C7: 0.01
B8: Annual Dividend Yield (%) | C8: 0.03
B9: Time Horizon (Months, 1-120) | C9: 12
B16: How this works
B17: • Three scenarios run side by side on the Calculation sheet, all from the same inputs above:
B18: 1) No-Dividend Fund — pure price growth, nothing paid out.
B19: 2) Dividend Reinvested — dividends buy more shares every month (compounds).
B20: 3) Dividend Paid as Cash — dividends land in a separate cash pile, portfolio grows from price only.
B21: • See the Summary sheet for the value of each scenario at your chosen Time Horizon, plus charts.
B22: • Blue/yellow cells are the only ones meant to be edited — everything else is a live formula.

Sheet Summary
B2: Summary @ Chosen Time Horizon
B3: Horizon (months): | C3: =Inputs!C9 -> 12
B5: Scenario | C5: Total Invested | D5: Ending Value | E5: Total Gain | F5: Return Multiple
B6: A: No-Dividend Fund | C6: =INDEX(Calculation!$R$3:$R$122,MATCH(Inputs!$C$9,Calculation!$A$3:$A$122,0)) -> 12000 | D6: =INDEX(Calculation!$F$3:$F$122,MATCH(Inputs!$C$9,Calculation!$A$3:$A$122,0)) -> 12809.328 | E6: =D6-C6 -> 809.32804 | F6: =IFERROR(D6/C6,0) -> 1.067444
B7: B: Dividend Reinvested | C7: =INDEX(Calculation!$R$3:$R$122,MATCH(Inputs!$C$9,Calculation!$A$3:$A$122,0)) -> 12000 | D7: =INDEX(Calculation!$K$3:$K$122,MATCH(Inputs!$C$9,Calculation!$A$3:$A$122,0)) -> 13021.116 | E7: =D7-C7 -> 1021.1159 | F7: =IFERROR(D7/C7,0) -> 1.085093
B8: C: Dividend Paid as Cash (portfolio + cash) | C8: =INDEX(Calculation!$R$3:$R$122,MATCH(Inputs!$C$9,Calculation!$A$3:$A$122,0)) -> 12000 | D8: =INDEX(Calculation!$P$3:$P$122,MATCH(Inputs!$C$9,Calculation!$A$3:$A$122,0))+INDEX(Calculation!$Q$3:$Q$122,MATCH(Inputs!$C$9,Calculation!$A$3:$A$122,0)) -> 13011.66 | E8: =D8-C8 -> 1011.6601 | F8: =IFERROR(D8/C8,0) -> 1.084305
B9: Note: Scenario C's cash dividends are simply summed, not reinvested at any return — they'd typically be withdrawn or held separately.

Sheet Calculation
C1: Scenario A – No Dividend Fund | G1: Scenario B – Dividend Reinvested | L1: Scenario C – Dividend Paid as Cash
A2: Month | B2: Contribution | C2: A: Begin Bal | D2: A: Bal+Contrib | E2: A: Growth $ | F2: A: End Bal | G2: B: Begin Bal | H2: B: Bal+Contrib | I2: B: Growth $ | J2: B: Dividend $ | K2: B: End Bal | L2: C: Begin Bal | M2: C: Bal+Contrib | N2: C: Growth $ | O2: C: Dividend $ (cash) | P2: C: End Bal (portfolio) | Q2: C: Cum. Cash Div | R2: Cumulative Invested
A3: 1 | B3: =Inputs!$C$6 -> 1000 | C3: =Inputs!$C$5 -> 0 | D3: =C3+B3 -> 1000 | E3: =D3*Inputs!$C$7 -> 10 | F3: =D3+E3 -> 1010 | G3: =Inputs!$C$5 -> 0 | H3: =G3+B3 -> 1000 | I3: =H3*Inputs!$C$7 -> 10 | J3: =H3*(Inputs!$C$8/12) -> 2.5 | K3: =H3+I3+J3 -> 1012.5 | L3: =Inputs!$C$5 -> 0 | M3: =L3+B3 -> 1000 | N3: =M3*Inputs!$C$7 -> 10 | O3: =M3*(Inputs!$C$8/12) -> 2.5 | P3: =M3+N3 -> 1010 | Q3: =O3 -> 2.5 | R3: =B3 -> 1000
A4: 2 | B4: =Inputs!$C$6 -> 1000 | C4: =F3 -> 1010 | D4: =C4+B4 -> 2010 | E4: =D4*Inputs!$C$7 -> 20.1 | F4: =D4+E4 -> 2030.1 | G4: =K3 -> 1012.5 | H4: =G4+B4 -> 2012.5 | I4: =H4*Inputs!$C$7 -> 20.125 | J4: =H4*(Inputs!$C$8/12) -> 5.03125 | K4: =H4+I4+J4 -> 2037.6562 | L4: =P3 -> 1010 | M4: =L4+B4 -> 2010 | N4: =M4*Inputs!$C$7 -> 20.1 | O4: =M4*(Inputs!$C$8/12) -> 5.025 | P4: =M4+N4 -> 2030.1 | Q4: =Q3+O4 -> 7.525 | R4: =R3+B4 -> 2000
A5: 3 | B5: =Inputs!$C$6 -> 1000 | C5: =F4 -> 2030.1 | D5: =C5+B5 -> 3030.1 | E5: =D5*Inputs!$C$7 -> 30.301 | F5: =D5+E5 -> 3060.401 | G5: =K4 -> 2037.6562 | H5: =G5+B5 -> 3037.6562 | I5: =H5*Inputs!$C$7 -> 30.376562 | J5: =H5*(Inputs!$C$8/12) -> 7.5941406 | K5: =H5+I5+J5 -> 3075.627 | L5: =P4 -> 2030.1 | M5: =L5+B5 -> 3030.1 | N5: =M5*Inputs!$C$7 -> 30.301 | O5: =M5*(Inputs!$C$8/12) -> 7.57525 | P5: =M5+N5 -> 3060.401 | Q5: =Q4+O5 -> 15.10025 | R5: =R4+B5 -> 3000
A6: 4 | B6: =Inputs!$C$6 -> 1000 | C6: =F5 -> 3060.401 | D6: =C6+B6 -> 4060.401 | E6: =D6*Inputs!$C$7 -> 40.60401 | F6: =D6+E6 -> 4101.005 | G6: =K5 -> 3075.627 | H6: =G6+B6 -> 4075.627 | I6: =H6*Inputs!$C$7 -> 40.75627 | J6: =H6*(Inputs!$C$8/12) -> 10.189067 | K6: =H6+I6+J6 -> 4126.5723 | L6: =P5 -> 3060.401 | M6: =L6+B6 -> 4060.401 | N6: =M6*Inputs!$C$7 -> 40.60401 | O6: =M6*(Inputs!$C$8/12) -> 10.151003 | P6: =M6+N6 -> 4101.005 | Q6: =Q5+O6 -> 25.251252 | R6: =R5+B6 -> 4000
A7: 5 | B7: =Inputs!$C$6 -> 1000 | C7: =F6 -> 4101.005 | D7: =C7+B7 -> 5101.005 | E7: =D7*Inputs!$C$7 -> 51.01005 | F7: =D7+E7 -> 5152.0151 | G7: =K6 -> 4126.5723 | H7: =G7+B7 -> 5126.5723 | I7: =H7*Inputs!$C$7 -> 51.265723 | J7: =H7*(Inputs!$C$8/12) -> 12.816431 | K7: =H7+I7+J7 -> 5190.6544 | L7: =P6 -> 4101.005 | M7: =L7+B7 -> 5101.005 | N7: =M7*Inputs!$C$7 -> 51.01005 | O7: =M7*(Inputs!$C$8/12) -> 12.752513 | P7: =M7+N7 -> 5152.0151 | Q7: =Q6+O7 -> 38.003765 | R7: =R6+B7 -> 5000
A8: 6 | B8: =Inputs!$C$6 -> 1000 | C8: =F7 -> 5152.0151 | D8: =C8+B8 -> 6152.0151 | E8: =D8*Inputs!$C$7 -> 61.520151 | F8: =D8+E8 -> 6213.5352 | G8: =K7 -> 5190.6544 | H8: =G8+B8 -> 6190.6544 | I8: =H8*Inputs!$C$7 -> 61.906544 | J8: =H8*(Inputs!$C$8/12) -> 15.476636 | K8: =H8+I8+J8 -> 6268.0376 | L8: =P7 -> 5152.0151 | M8: =L8+B8 -> 6152.0151 | N8: =M8*Inputs!$C$7 -> 61.520151 | O8: =M8*(Inputs!$C$8/12) -> 15.380038 | P8: =M8+N8 -> 6213.5352 | Q8: =Q7+O8 -> 53.383803 | R8: =R7+B8 -> 6000
A9: 7 | B9: =Inputs!$C$6 -> 1000 | C9: =F8 -> 6213.5352 | D9: =C9+B9 -> 7213.5352 | E9: =D9*Inputs!$C$7 -> 72.135352 | F9: =D9+E9 -> 7285.6706 | G9: =K8 -> 6268.0376 | H9: =G9+B9 -> 7268.0376 | I9: =H9*Inputs!$C$7 -> 72.680376 | J9: =H9*(Inputs!$C$8/12) -> 18.170094 | K9: =H9+I9+J9 -> 7358.8881 | L9: =P8 -> 6213.5352 | M9: =L9+B9 -> 7213.5352 | N9: =M9*Inputs!$C$7 -> 72.135352 | O9: =M9*(Inputs!$C$8/12) -> 18.033838 | P9: =M9+N9 -> 7285.6706 | Q9: =Q8+O9 -> 71.417641 | R9: =R8+B9 -> 7000
A10: 8 | B10: =Inputs!$C$6 -> 1000 | C10: =F9 -> 7285.6706 | D10: =C10+B10 -> 8285.6706 | E10: =D10*Inputs!$C$7 -> 82.856706 | F10: =D10+E10 -> 8368.5273 | G10: =K9 -> 7358.8881 | H10: =G10+B10 -> 8358.8881 | I10: =H10*Inputs!$C$7 -> 83.588881 | J10: =H10*(Inputs!$C$8/12) -> 20.89722 | K10: =H10+I10+J10 -> 8463.3742 | L10: =P9 -> 7285.6706 | M10: =L10+B10 -> 8285.6706 | N10: =M10*Inputs!$C$7 -> 82.856706 | O10: =M10*(Inputs!$C$8/12) -> 20.714176 | P10: =M10+N10 -> 8368.5273 | Q10: =Q9+O10 -> 92.131817 | R10: =R9+B10 -> 8000
A11: 9 | B11: =Inputs!$C$6 -> 1000 | C11: =F10 -> 8368.5273 | D11: =C11+B11 -> 9368.5273 | E11: =D11*Inputs!$C$7 -> 93.685273 | F11: =D11+E11 -> 9462.2125 | G11: =K10 -> 8463.3742 | H11: =G11+B11 -> 9463.3742 | I11: =H11*Inputs!$C$7 -> 94.633742 | J11: =H11*(Inputs!$C$8/12) -> 23.658435 | K11: =H11+I11+J11 -> 9581.6664 | L11: =P10 -> 8368.5273 | M11: =L11+B11 -> 9368.5273 | N11: =M11*Inputs!$C$7 -> 93.685273 | O11: =M11*(Inputs!$C$8/12) -> 23.421318 | P11: =M11+N11 -> 9462.2125 | Q11: =Q10+O11 -> 115.55314 | R11: =R10+B11 -> 9000
A12: 10 | B12: =Inputs!$C$6 -> 1000 | C12: =F11 -> 9462.2125 | D12: =C12+B12 -> 10462.213 | E12: =D12*Inputs!$C$7 -> 104.62213 | F12: =D12+E12 -> 10566.835 | G12: =K11 -> 9581.6664 | H12: =G12+B12 -> 10581.666 | I12: =H12*Inputs!$C$7 -> 105.81666 | J12: =H12*(Inputs!$C$8/12) -> 26.454166 | K12: =H12+I12+J12 -> 10713.937 | L12: =P11 -> 9462.2125 | M12: =L12+B12 -> 10462.213 | N12: =M12*Inputs!$C$7 -> 104.62213 | O12: =M12*(Inputs!$C$8/12) -> 26.155531 | P12: =M12+N12 -> 10566.835 | Q12: =Q11+O12 -> 141.70867 | R12: =R11+B12 -> 10000
A13: 11 | B13: =Inputs!$C$6 -> 1000 | C13: =F12 -> 10566.835 | D13: =C13+B13 -> 11566.835 | E13: =D13*Inputs!$C$7 -> 115.66835 | F13: =D13+E13 -> 11682.503 | G13: =K12 -> 10713.937 | H13: =G13+B13 -> 11713.937 | I13: =H13*Inputs!$C$7 -> 117.13937 | J13: =H13*(Inputs!$C$8/12) -> 29.284843 | K13: =H13+I13+J13 -> 11860.361 | L13: =P12 -> 10566.835 | M13: =L13+B13 -> 11566.835 | N13: =M13*Inputs!$C$7 -> 115.66835 | O13: =M13*(Inputs!$C$8/12) -> 28.917087 | P13: =M13+N13 -> 11682.503 | Q13: =Q12+O13 -> 170.62575 | R13: =R12+B13 -> 11000
A14: 12 | B14: =Inputs!$C$6 -> 1000 | C14: =F13 -> 11682.503 | D14: =C14+B14 -> 12682.503 | E14: =D14*Inputs!$C$7 -> 126.82503 | F14: =D14+E14 -> 12809.328 | G14: =K13 -> 11860.361 | H14: =G14+B14 -> 12860.361 | I14: =H14*Inputs!$C$7 -> 128.60361 | J14: =H14*(Inputs!$C$8/12) -> 32.150904 | K14: =H14+I14+J14 -> 13021.116 | L14: =P13 -> 11682.503 | M14: =L14+B14 -> 12682.503 | N14: =M14*Inputs!$C$7 -> 126.82503 | O14: =M14*(Inputs!$C$8/12) -> 31.706258 | P14: =M14+N14 -> 12809.328 | Q14: =Q13+O14 -> 202.33201 | R14: =R13+B14 -> 12000
A15: 13 | B15: =Inputs!$C$6 -> 1000 | C15: =F14 -> 12809.328 | D15: =C15+B15 -> 13809.328 | E15: =D15*Inputs!$C$7 -> 138.09328 | F15: =D15+E15 -> 13947.421 | G15: =K14 -> 13021.116 | H15: =G15+B15 -> 14021.116 | I15: =H15*Inputs!$C$7 -> 140.21116 | J15: =H15*(Inputs!$C$8/12) -> 35.05279 | K15: =H15+I15+J15 -> 14196.38 | L15: =P14 -> 12809.328 | M15: =L15+B15 -> 13809.328 | N15: =M15*Inputs!$C$7 -> 138.09328 | O15: =M15*(Inputs!$C$8/12) -> 34.52332 | P15: =M15+N15 -> 13947.421 | Q15: =Q14+O15 -> 236.85533 | R15: =R14+B15 -> 13000
... A122: 120 | B122: =Inputs!$C$6 -> 1000 | C122: =F121 -> 229038.69 | D122: =C122+B122 -> 230038.69 | E122: =D122*Inputs!$C$7 -> 2300.3869 | F122: =D122+E122 -> 232339.08 | G122: =K121 -> 274217.06 | H122: =G122+B122 -> 275217.06 | I122: =H122*Inputs!$C$7 -> 2752.1706 | J122: =H122*(Inputs!$C$8/12) -> 688.04265 | K122: =H122+I122+J122 -> 278657.27 | L122: =P121 -> 229038.69 | M122: =L122+B122 -> 230038.69 | N122: =M122*Inputs!$C$7 -> 2300.3869 | O122: =M122*(Inputs!$C$8/12) -> 575.09672 | P122: =M122+N122 -> 232339.08 | Q122: =Q121+O122 -> 28084.769 | R122: =R121+B122 -> 120000
